aws_snippets/__init__.py
aws_snippets-2024.1.0.0.dist-info/METADATA
aws_snippets-2024.1.0.0.dist-info/WHEEL
aws_snippets-2024.1.0.0.dist-info/RECORD
